{"chords":[{"id":"b2ae0cc82cffb7f96c925bb4bdfc36f4ea70b290","name":"C#5","complexity":0.977193,"chordPattern":{"e4":"4","b":"2","g":"","d":"","a":"","e2":""},"complexityRank":1},{"id":"8694ff3a0a523920f1e163886915e60f326da619","name":"C#5","complexity":1.231579,"chordPattern":{"e4":"9","b":"9","g":"6","d":"","a":"","e2":""},"complexityRank":2},{"id":"52fb2551d9a26ec79bab35c44f403adc5fb350b5","name":"C#5","complexity":2.0210526,"chordPattern":{"e4":"","b":"","g":"6","d":"6","a":"4","e2":""},"complexityRank":3},{"id":"9e38aa3513a7f9932b13c356b62b7312346c64d2","name":"C#5","complexity":2.1877193,"chordPattern":{"e4":"","b":"","g":"","d":"6","a":"4","e2":""},"complexityRank":4},{"id":"02a39a4cdba25b01ef3d693d61a970ffe9cc3d39","name":"C#5","complexity":2.240351,"chordPattern":{"e4":"16","b":"14","g":"","d":"","a":"","e2":""},"complexityRank":5},{"id":"039a8594a1cd17648ce0f49a61e5401db55c35b3","name":"C#5","complexity":2.3982456,"chordPattern":{"e4":"","b":"9","g":"6","d":"","a":"","e2":""},"complexityRank":6},{"id":"91a569a1bc8ad976fe96e35ef65d0aad77090249","name":"C#5","complexity":2.5473685,"chordPattern":{"e4":"","b":"","g":"","d":"11","a":"11","e2":"9"},"complexityRank":7},{"id":"65d404e1bc8727029c438979e1365ab088df20ac","name":"C#5","complexity":2.714035,"chordPattern":{"e4":"","b":"","g":"","d":"","a":"11","e2":"9"},"complexityRank":8},{"id":"f100e10cc2e77ce0f9db7a2156ba6bbf8663a4ca","name":"C#5","complexity":2.7578948,"chordPattern":{"e4":"","b":"14","g":"13","d":"11","a":"","e2":""},"complexityRank":9},{"id":"4a18228428bfaaa16fd1bce3e6568095c6095446","name":"C#5","complexity":2.9245615,"chordPattern":{"e4":"","b":"","g":"13","d":"11","a":"","e2":""},"complexityRank":10},{"id":"d741ade8761cb5073dd032030eeccbe95d08cb8d","name":"C#5","complexity":3.2842104,"chordPattern":{"e4":"","b":"","g":"18","d":"18","a":"16","e2":""},"complexityRank":11},{"id":"ea92e8a1c666519107bfe553b25541e4fae08e38","name":"C#5","complexity":3.4508772,"chordPattern":{"e4":"","b":"","g":"","d":"18","a":"16","e2":""},"complexityRank":12}]}