{"chords":[{"id":"a8366f5e1c575ff9dc68ea61f6d493a9eec1fd00","name":"C#sus2","complexity":0.37192982,"chordPattern":{"e4":"4","b":"2","g":"1","d":"1","a":"4","e2":""},"complexityRank":1},{"id":"3ba5f61eb3ff16c486ecd1e4aaed4cd2fdd1af24","name":"C#sus2","complexity":0.37192982,"chordPattern":{"e4":"4","b":"4","g":"1","d":"1","a":"4","e2":""},"complexityRank":2},{"id":"be332ce31e28e5474a9dc26a94dbdbc7982175d8","name":"C#sus2","complexity":0.6877193,"chordPattern":{"e4":"4","b":"4","g":"6","d":"6","a":"4","e2":""},"complexityRank":3},{"id":"cef3f561d776a8a8ceb0a88c64263cbe6d7f7f3b","name":"C#sus2","complexity":0.73157895,"chordPattern":{"e4":"9","b":"9","g":"6","d":"6","a":"6","e2":"9"},"complexityRank":4},{"id":"fbce2d5035f6c1439b3930e4c2b78fecc3ecebd5","name":"C#sus2","complexity":1.0210526,"chordPattern":{"e4":"4","b":"4","g":"6","d":"","a":"","e2":""},"complexityRank":5},{"id":"04303cab8a1913ff5c59a220f4442d7c632fc943","name":"C#sus2","complexity":1.2754385,"chordPattern":{"e4":"9","b":"9","g":"8","d":"11","a":"","e2":""},"complexityRank":6},{"id":"3253aebcf8537f78e88e8f4c074a87219a75e2f5","name":"C#sus2","complexity":1.2754385,"chordPattern":{"e4":"11","b":"9","g":"8","d":"11","a":"","e2":""},"complexityRank":7},{"id":"444e47e120df9fa1d74201ec3941dc41a2a3280a","name":"C#sus2","complexity":1.5385965,"chordPattern":{"e4":"","b":"2","g":"1","d":"1","a":"4","e2":""},"complexityRank":8},{"id":"33031b12feffe9f4fcc615a44e1e8f450c39a69a","name":"C#sus2","complexity":1.5385965,"chordPattern":{"e4":"","b":"4","g":"1","d":"1","a":"4","e2":""},"complexityRank":9},{"id":"85de1253ca56a2d60d0ee02e2b87b76a3670f1aa","name":"C#sus2","complexity":1.5912281,"chordPattern":{"e4":"11","b":"14","g":"13","d":"11","a":"","e2":""},"complexityRank":10},{"id":"901d264b5e4544965bdd71d47792c35daa9d40e1","name":"C#sus2","complexity":1.6350877,"chordPattern":{"e4":"16","b":"14","g":"13","d":"13","a":"16","e2":""},"complexityRank":11},{"id":"02bff2dd4273bfbeca53bd14dd27ef2e1ebd3a51","name":"C#sus2","complexity":1.6350877,"chordPattern":{"e4":"16","b":"16","g":"13","d":"13","a":"16","e2":""},"complexityRank":12},{"id":"364b1afb393196ab684c1843396379e0a94be1ef","name":"C#sus2","complexity":1.7052631,"chordPattern":{"e4":"","b":"","g":"1","d":"1","a":"4","e2":""},"complexityRank":13},{"id":"179adc220c6bcd9150998514887f7df6fc7d8e9b","name":"C#sus2","complexity":1.854386,"chordPattern":{"e4":"","b":"4","g":"6","d":"6","a":"4","e2":""},"complexityRank":14},{"id":"530c71fcaaac9970a06657510158eed1a70e0371","name":"C#sus2","complexity":1.8982456,"chordPattern":{"e4":"","b":"9","g":"6","d":"6","a":"6","e2":"9"},"complexityRank":15},{"id":"de00841d401bdd54fe8afea736ed9a9ed13d8440","name":"C#sus2","complexity":1.8982456,"chordPattern":{"e4":"","b":"9","g":"8","d":"6","a":"6","e2":"9"},"complexityRank":16},{"id":"eac9d33b6a7de3b790fc6da03269614d38f624fa","name":"C#sus2","complexity":1.9508772,"chordPattern":{"e4":"16","b":"16","g":"18","d":"18","a":"16","e2":""},"complexityRank":17},{"id":"0278f8462e00842b00e6bea2b39534c46ecb3d1f","name":"C#sus2","complexity":2.0649123,"chordPattern":{"e4":"","b":"","g":"6","d":"6","a":"6","e2":"9"},"complexityRank":18},{"id":"9a38f7b13efd9373f01971f262ada022ca79c0e9","name":"C#sus2","complexity":2.0649123,"chordPattern":{"e4":"","b":"","g":"8","d":"6","a":"6","e2":"9"},"complexityRank":19},{"id":"72808c807449e2bfbb03f4e838326d32be93f35c","name":"C#sus2","complexity":2.231579,"chordPattern":{"e4":"","b":"","g":"","d":"6","a":"6","e2":"9"},"complexityRank":20},{"id":"f0a6fa87da17846913fa2dc6d3ddc8259dd8634e","name":"C#sus2","complexity":2.2754385,"chordPattern":{"e4":"","b":"","g":"8","d":"11","a":"11","e2":"9"},"complexityRank":21},{"id":"710973cdc407b836a6b9c41529923097e1e6f623","name":"C#sus2","complexity":2.2842104,"chordPattern":{"e4":"16","b":"16","g":"18","d":"","a":"","e2":""},"complexityRank":22},{"id":"150cc785c1aa08856cb24ed34119790958c2aa4e","name":"C#sus2","complexity":2.4421053,"chordPattern":{"e4":"","b":"9","g":"8","d":"11","a":"","e2":""},"complexityRank":23},{"id":"8f7f9d19d5d59e162b30ba32b6c411cfaa758383","name":"C#sus2","complexity":2.8017545,"chordPattern":{"e4":"","b":"14","g":"13","d":"13","a":"16","e2":""},"complexityRank":24},{"id":"2c1ba87fbcaed604f2ea8d9fd77d9f9eeaa197b3","name":"C#sus2","complexity":2.8017545,"chordPattern":{"e4":"","b":"16","g":"13","d":"13","a":"16","e2":""},"complexityRank":25},{"id":"e149dca02d95940b89adee0de2f445e4191b60fc","name":"C#sus2","complexity":2.968421,"chordPattern":{"e4":"","b":"","g":"13","d":"13","a":"16","e2":""},"complexityRank":26},{"id":"68591725f5c832c8c3ed1bfe20b93f7e4f342566","name":"C#sus2","complexity":3.117544,"chordPattern":{"e4":"","b":"16","g":"18","d":"18","a":"16","e2":""},"complexityRank":27}]}