{"chords":[{"id":"da3009b756e8f033ab7023c4c46b195386c91d92","name":"Dm","complexity":0.33333334,"chordPattern":{"e4":"","b":"","g":"0","d":"2","a":"3","e2":"1"},"complexityRank":1},{"id":"0facff178da93c3baf7f0176bd0f3c1daa1e83ad","name":"Dm","complexity":0.79298246,"chordPattern":{"e4":"","b":"5","g":"7","d":"7","a":"6","e2":"5"},"complexityRank":2},{"id":"1e19fed9713bc7246658ac253fc44dda62bf0252","name":"Dm","complexity":1.1263158,"chordPattern":{"e4":"","b":"","g":"","d":"7","a":"6","e2":"5"},"complexityRank":3},{"id":"360fcb02d9c8c912b031bf0655a4d04f8f9a6215","name":"Dm","complexity":1.1526315,"chordPattern":{"e4":"10","b":"12","g":"12","d":"10","a":"10","e2":"10"},"complexityRank":4},{"id":"0f758f41ef075f099b891c1149c4a5278387a330","name":"Dm","complexity":1.1526315,"chordPattern":{"e4":"10","b":"12","g":"12","d":"10","a":"10","e2":"13"},"complexityRank":5},{"id":"bf212a5026c3c4dde43f0bf21583affe89ebc2a3","name":"Dm","complexity":1.4859649,"chordPattern":{"e4":"","b":"","g":"12","d":"10","a":"10","e2":"10"},"complexityRank":6},{"id":"264f6483770498b8622c40e1d09b5376ac95db2f","name":"Dm","complexity":1.4859649,"chordPattern":{"e4":"","b":"","g":"12","d":"10","a":"10","e2":"13"},"complexityRank":7},{"id":"b945ee1dad649dca505022207395aaea46042c5f","name":"Dm","complexity":1.6438596,"chordPattern":{"e4":"","b":"5","g":"3","d":"2","a":"3","e2":""},"complexityRank":8},{"id":"ac4c82cea484edbc62f12ccd58dfa3df3e85a496","name":"Dm","complexity":1.6964912,"chordPattern":{"e4":"","b":"","g":"12","d":"14","a":"15","e2":"13"},"complexityRank":9},{"id":"8900dade8f108dc5e6f5e1645e8c27952f435219","name":"Dm","complexity":1.8105264,"chordPattern":{"e4":"","b":"5","g":"3","d":"2","a":"","e2":""},"complexityRank":10},{"id":"f9adeae98e9a742c3e60d516bfed9c0ec667e6cd","name":"Dm","complexity":1.9596491,"chordPattern":{"e4":"","b":"5","g":"7","d":"7","a":"6","e2":""},"complexityRank":11},{"id":"1e9f7f06c6a22585e4a44aa54a30b85479871e82","name":"Dm","complexity":2.0035088,"chordPattern":{"e4":"10","b":"8","g":"7","d":"7","a":"10","e2":""},"complexityRank":12},{"id":"b04c1a1a92da2bbd6bd80041f819495b613b5243","name":"Dm","complexity":2.0561404,"chordPattern":{"e4":"","b":"17","g":"19","d":"19","a":"18","e2":"17"},"complexityRank":13},{"id":"10e0316d00f00b97f1cf65e0744ec735bba7f12f","name":"Dm","complexity":2.1701756,"chordPattern":{"e4":"10","b":"8","g":"7","d":"7","a":"","e2":""},"complexityRank":14},{"id":"374f2f24e0f6bbe9aa70642958b5e14dea5dce89","name":"Dm","complexity":2.1701756,"chordPattern":{"e4":"10","b":"8","g":"7","d":"10","a":"","e2":""},"complexityRank":15},{"id":"e70f70bdcc730448cdc52bea44aec17c1135d3b3","name":"Dm","complexity":2.3192983,"chordPattern":{"e4":"10","b":"12","g":"12","d":"10","a":"10","e2":""},"complexityRank":16},{"id":"f309eaffa24897cd587ec2c344a385aa9b104b6a","name":"Dm","complexity":2.336842,"chordPattern":{"e4":"10","b":"8","g":"7","d":"","a":"","e2":""},"complexityRank":17},{"id":"a7e5d9a7fc3ada7ed9b1c811f11c100cd006036c","name":"Dm","complexity":2.3894737,"chordPattern":{"e4":"","b":"","g":"","d":"19","a":"18","e2":"17"},"complexityRank":18},{"id":"ee8962d2a044d03cdfb80c1a39019167a1b93dad","name":"Dm","complexity":2.485965,"chordPattern":{"e4":"10","b":"12","g":"12","d":"10","a":"","e2":""},"complexityRank":19},{"id":"76317dc25b4019217dccdb745bee39ba93e82152","name":"Dm","complexity":2.6526315,"chordPattern":{"e4":"","b":"","g":"12","d":"10","a":"10","e2":""},"complexityRank":20},{"id":"adf7dce6c776966fcaaeec5861b75d3fd14b2140","name":"Dm","complexity":2.9070175,"chordPattern":{"e4":"","b":"17","g":"15","d":"14","a":"15","e2":""},"complexityRank":21},{"id":"13da8eccb7473e586d8429d7312660d7c5d9344a","name":"Dm","complexity":3.0736842,"chordPattern":{"e4":"","b":"17","g":"15","d":"14","a":"","e2":""},"complexityRank":22},{"id":"33da31987498702377ef286601b171cfa5e59c31","name":"Dm","complexity":3.222807,"chordPattern":{"e4":"","b":"17","g":"19","d":"19","a":"18","e2":""},"complexityRank":23}]}